LeanMem/__init__.py
leanmem-0.0.1.dist-info/METADATA
leanmem-0.0.1.dist-info/WHEEL
leanmem-0.0.1.dist-info/top_level.txt
leanmem-0.0.1.dist-info/RECORD
