Metadata-Version: 2.4
Name: leanmem
Version: 0.0.1
Summary: Lean Memory.
Requires-Python: >=3.8
